Metadata-Version: 2.1
Name: figures-07659443
Version: 0.1
Summary: With this program you can find areas and perimeters of 	different circles, triangles and squares
Author-email: nevdokimov777@gmail.com
